LICENSE
MANIFEST.in
README.md
setup.py
buildz/__init__.py
buildz/__main__.py
buildz/argx.py
buildz/base.py
buildz/cmd.py
buildz/confz.py
buildz/dz.py
buildz/log.py
buildz/logz.py
buildz/path.py
buildz/pathz.py
buildz/pyz.py
buildz/tls.py
buildz/tools.py
buildz.egg-info/PKG-INFO
buildz.egg-info/SOURCES.txt
buildz.egg-info/dependency_links.txt
buildz.egg-info/top_level.txt
buildz/_dz/conf.py
buildz/_dz/confx.py
buildz/_dz/mapz.py
buildz/_dz/oconf.py
buildz/_dz/omapz.py
buildz/argz/__init__.py
buildz/argz/argz.py
buildz/argz/callz.py
buildz/argz/conf_argz.py
buildz/argz/conf_callz.py
buildz/argz/evalx.py
buildz/argz/init.py
buildz/argz/test.py
buildz/argz/test_call.py
buildz/argz_bk/__init__.py
buildz/argz_bk/argz.py
buildz/argz_bk/build.py
buildz/argz_bk/callz.py
buildz/argz_bk/evalx.py
buildz/argz_bk/test.py
buildz/argz_bk/test_obj.py
buildz/argz_bk/testx.py
buildz/argz_bk/tests/conf.js
buildz/auto/__init__.py
buildz/auto/cache.py
buildz/auto/config.py
buildz/auto/dbs.py
buildz/auto/deal.py
buildz/auto/deal_list.py
buildz/auto/deal_type.py
buildz/auto/defs.py
buildz/auto/factory.py
buildz/auto/init.py
buildz/auto/log.py
buildz/auto/request.py
buildz/auto/run.py
buildz/auto/save.py
buildz/auto/verify.py
buildz/auto/test/test.py
buildz/auto/test/xtest.py
buildz/auto/test/res/cache/cache.js
buildz/auto/test/res/config/base.js
buildz/auto/test/res/config/config.js
buildz/auto/test/res/data/fp.js
buildz/auto/test/res/data/item1.js
buildz/auto/test/res/data/item2.js
buildz/auto/test/res/data/test.js
buildz/cachez/__init__.py
buildz/cachez/cache.py
buildz/confz_test/argx.js
buildz/confz_test/conf.js
buildz/confz_test/test.js
buildz/confz_test/test.py
buildz/db/__init__.py
buildz/db/__main__.py
buildz/db/install.txt
buildz/db/run.conf
buildz/db/runz.py
buildz/db/sc.py
buildz/db/subrun.py
buildz/db/subsc.py
buildz/db/tls.py
buildz/db/dv/__init__.py
buildz/db/dv/basez.py
buildz/db/dv/clickhousez.py
buildz/db/dv/mysqlz.py
buildz/db/dv/oraclez.py
buildz/db/dv/orm.py
buildz/db/dv/postgresqlz.py
buildz/db/dv/sqlite3z.py
buildz/db/dv/structz.py
buildz/db/dv/lib/readme
buildz/demo/test.py
