Metadata-Version: 2.1
Name: buildz
Version: 0.9.11
Summary: 配置读写（基于json格式进行简化）、ioc、以及其他工具代码。a json-base file format's read and write code by python, and codes to read and product object from configure file in such format(ioc), and other tool codes
Home-page: https://github.com/buildCodeZ/buildz
Author: Zzz
Author-email: 1309458652@qq.com
License: Apache License 2.0
Keywords: buildz
Platform: any
License-File: LICENSE
